[{"beCommentWeiboId":"d41d8cd98f00b204e9800998ecf8427e","beForwardWeiboId":"d41d8cd98f00b204e9800998ecf8427e","catchTime":"1387809560","commentCount":"0","content":"【嫦娥三号两器互拍成功月球车五星红旗清晰】12月16日电第一面登上月球的五星红旗15日晚通过电视直播“亮相”。中国探月工程总指挥马兴瑞随后宣布，嫦娥三号任务取得圆满成功。","createTime":"1387662008","info1":"","info2":"","info3":"","mlevel":"","musicurl":[],"pic_list":["http:\/\/ww2.sinaimg.cn\/thumbnail\/d66c8d70jw1ebs1i8fgpzj20dd09xmxv.jpg"],"praiseCount":"0","reportCount":"0","source":"皮皮时光机","userId":"699b751fa64e3ce73c3df018782cdba9","videourl":[],"weiboId":"1806695a7f816cbf090ff2883b72ad9e","weiboUrl":"21560ffcdf8bc40ae5092d28e9b49b13"}]
[{"beCommentWeiboId":"d41d8cd98f00b204e9800998ecf8427e","beForwardWeiboId":"d41d8cd98f00b204e9800998ecf8427e","catchTime":"1387809560","commentCount":"78","content":"这次嫦娥三号奔月成功，云南天文台昆明站的40米直径射电望远镜起了大作用。它和位于北京、乌鲁木齐等地的另外几台射电望远镜一起，在“嫦娥奔月”时监控探测器位置，为@月球车玉兔和嫦娥三号提供数据服务。果壳网友@iGreeny@花落成蚀近距离拍下了它威武雄壮的身影，更多大图：http://t.cn/8kl5UUD","createTime":"1387637631","info1":"","info2":"","info3":"","mlevel":"","musicurl":[],"pic_list":["http:\/\/ww1.sinaimg.cn\/thumbnail\/6e53d84fjw1ebrpqnn6pyj20c80qf774.jpg"],"praiseCount":"","reportCount":"200","source":"专业版微博","userId":"81d093bbb9ead006e47624f2b13cf884","videourl":[],"weiboId":"13458941c9c4f8a12790cbb98821148d","weiboUrl":"617023ad363a446b18e7f4a322934587"}]
[{"beCommentWeiboId":"d41d8cd98f00b204e9800998ecf8427e","beForwardWeiboId":"13458941c9c4f8a12790cbb98821148d","catchTime":"1387809560","commentCount":"0","content":"好萌哦！//@月球车玉兔:这次我和嫦娥三号能成功抵达月球，在这边拍的照片能让师父们收到，都要好好感谢这几位射电望远镜大叔！这段时间，月亮升起他们就得上班，朝着月球的方向接收我们发回的信息。大家猜，望远镜旁边那个楼的窗帘为什么都捂得这么严实？才不是果壳君说的什么有人在打游戏……","createTime":"1387660570","info1":"","info2":"","info3":"","mlevel":"","musicurl":[],"pic_list":[],"praiseCount":"0","reportCount":"0","source":"新浪微博","userId":"b13674d3b0f79567aa4b64ee94d6cb0e","videourl":[],"weiboId":"7cee52d850b15ca817d626787a5cb52f","weiboUrl":"c27ee67b8da98ae02faa7d70c5c5fdac"}]
[{"beCommentWeiboId":"d41d8cd98f00b204e9800998ecf8427e","beForwardWeiboId":"d41d8cd98f00b204e9800998ecf8427e","catchTime":"1387809560","commentCount":"78","content":"这次嫦娥三号奔月成功，云南天文台昆明站的40米直径射电望远镜起了大作用。它和位于北京、乌鲁木齐等地的另外几台射电望远镜一起，在“嫦娥奔月”时监控探测器位置，为@月球车玉兔和嫦娥三号提供数据服务。果壳网友@iGreeny@花落成蚀近距离拍下了它威武雄壮的身影，更多大图：http://t.cn/8kl5UUD","createTime":"1387637631","info1":"","info2":"","info3":"","mlevel":"","musicurl":[],"pic_list":["http:\/\/ww1.sinaimg.cn\/thumbnail\/6e53d84fjw1ebrpqnn6pyj20c80qf774.jpg"],"praiseCount":"","reportCount":"200","source":"专业版微博","userId":"81d093bbb9ead006e47624f2b13cf884","videourl":[],"weiboId":"13458941c9c4f8a12790cbb98821148d","weiboUrl":"617023ad363a446b18e7f4a322934587"}]
[{"beCommentWeiboId":"d41d8cd98f00b204e9800998ecf8427e","beForwardWeiboId":"13458941c9c4f8a12790cbb98821148d","catchTime":"1387809560","commentCount":"0","content":"//@月球车玉兔:这次我和嫦娥三号能成功抵达月球，在这边拍的照片能让师父们收到，都要好好感谢这几位射电望远镜大叔！这段时间，月亮升起他们就得上班，朝着月球的方向接收我们发回的信息。大家猜，望远镜旁边那个楼的窗帘为什么都捂得这么严实？才不是果壳君说的什么有人在打游戏……","createTime":"1387660502","info1":"","info2":"","info3":"","mlevel":"","musicurl":[],"pic_list":[],"praiseCount":"0","reportCount":"0","source":"新浪微博","userId":"5f1ab74f44d7d92eedcd4a8d73ef717b","videourl":[],"weiboId":"e7e49b7a7aaea4979cfa4039dc60a036","weiboUrl":"352a72cc46d0253ffd23f8412345de71"}]
[{"beCommentWeiboId":"d41d8cd98f00b204e9800998ecf8427e","beForwardWeiboId":"d41d8cd98f00b204e9800998ecf8427e","catchTime":"1387809560","commentCount":"0","content":"【嫦娥三号今晚落月须闯“五关”经历黑色12分钟】北京时间12月14日，嫦娥落月，即将在今晚9点多上演。由着陆器和“玉兔”号月球车组成的“嫦娥三号”预计将于今晚在月球虹湾区软着陆，这将是此次嫦娥三号任务最大的看点。明晚，月球车要和着陆器“说再见”","createTime":"1387660333","info1":"","info2":"","info3":"","mlevel":"","musicurl":[],"pic_list":["http:\/\/ww3.sinaimg.cn\/thumbnail\/d888f0e8jw1ebs0p6elezj20d2080glq.jpg"],"praiseCount":"0","reportCount":"0","source":"皮皮时光机","userId":"e1c8387dee267e28ec742d50f1b586f8","videourl":[],"weiboId":"2051f5f4ccdb87d246d9570ca6db2cd3","weiboUrl":"01f995502f323d318ad06f947940dae3"}]
