[{"beCommentWeiboId":"d41d8cd98f00b204e9800998ecf8427e","beForwardWeiboId":"d41d8cd98f00b204e9800998ecf8427e","catchTime":"1387807683","commentCount":"0","content":"与刚弟散步，他提到即将发射的嫦娥三号：科技的力量多伟大啊！我们将从此把月亮的秘密搞得清清楚楚了。我：搞清楚了又怎么了？你对看不清楚的东西那么想搞清楚？他不屑：当然，这就是科学精神。我：哦，探密，科技，力量，你衷情这些呀。他：不行吗？我：你抬头看，十六的月亮多美啊，上去还能写诗么？","createTime":"1379691639","info1":"","info2":"","info3":"","mlevel":"","musicurl":[],"pic_list":[],"praiseCount":"0","reportCount":"0","source":"新浪微博","userId":"221c5c97b626210e74157c6693ceaea3","videourl":[],"weiboId":"f8db702d3e8fbdc19ec670070e2b901f","weiboUrl":"b9d843dfe7643679616caf76280fe113"}]
[{"beCommentWeiboId":"d41d8cd98f00b204e9800998ecf8427e","beForwardWeiboId":"d41d8cd98f00b204e9800998ecf8427e","catchTime":"1387807683","commentCount":"0","content":"【嫦娥三号今年年底择机发射将实现月面软着陆】国防科工局消息，嫦娥三号任务已由研制建设阶段转入发射实施阶段，将于今年年底由西昌卫星发射中心择机发射。嫦娥三号承担“落月”任务，将实现月面软着陆，开展就位探测和月面巡视勘察。这将是我国航天器首次地外天体软着陆。","createTime":"1379691191","info1":"","info2":"","info3":"","mlevel":"","musicurl":[],"pic_list":["http:\/\/ww1.sinaimg.cn\/thumbnail\/8c81ad76jw1e8tdw3wladj20bk09pmxd.jpg"],"praiseCount":"0","reportCount":"0","source":"vivo_Xplay","userId":"b5710ea915c0060bfd0b11c12c1c0781","videourl":[],"weiboId":"5e1a274cb7c74a0afed21d3bf75f941e","weiboUrl":"edda229ab1996a5f8cb92ffd3d012bd9"}]
[{"beCommentWeiboId":"d41d8cd98f00b204e9800998ecf8427e","beForwardWeiboId":"d41d8cd98f00b204e9800998ecf8427e","catchTime":"1387807683","commentCount":"3","content":"嫦娥三号","createTime":"1379689479","info1":"","info2":"","info3":"","mlevel":"","musicurl":[],"pic_list":["http:\/\/ww2.sinaimg.cn\/thumbnail\/a86aecdejw1e8td2fqt81j20hs0nqq4f.jpg"],"praiseCount":"2","reportCount":"0","source":"Weico.iPhone","userId":"41583b2a73ee515a45931229eb586943","videourl":[],"weiboId":"b032716edf56cb361e26ecac886b75d3","weiboUrl":"8f9c51dc15823e238c54025098f8e777"}]
[{"beCommentWeiboId":"d41d8cd98f00b204e9800998ecf8427e","beForwardWeiboId":"d41d8cd98f00b204e9800998ecf8427e","catchTime":"1387807683","commentCount":"0","content":"由中国航天科技集团公司研制的嫦娥三号探测器，9月12日运抵西昌卫星发射中心，标志着奔月之旅迈出关键一步。嫦娥三号探测器将执行我国航天器首次地外天体软着陆，开展就位探测和月面巡视勘察。按照计划，嫦娥三号将于今年年底在西昌卫星发射中心择机发射。","createTime":"1379689412","info1":"","info2":"","info3":"","mlevel":"","musicurl":[],"pic_list":["http:\/\/ww1.sinaimg.cn\/thumbnail\/660e6048tw1e8td13ktozj20go0b7jt0.jpg"],"praiseCount":"0","reportCount":"0","source":"新浪微博","userId":"61ddf1e157f147112b7b01c99084b8a1","videourl":[],"weiboId":"42fa8b632797de0c5f0b9fe51c3ec88b","weiboUrl":"ee8b40a9af7f750e511031730f2e7a46"}]
