[{"beCommentWeiboId":"d41d8cd98f00b204e9800998ecf8427e","beForwardWeiboId":"d41d8cd98f00b204e9800998ecf8427e","catchTime":"1387807416","commentCount":"1","content":"#天文简报#【每日天文大事件播报】:1.哈勃望远镜已在小行星带发现迄今为止最奇怪的一个天体，这块岩石像失控的草坪洒水喷头一样旋转，向外喷出六条像彗尾的尘埃尾巴。2.嫦娥三号将采用核动力推进，如能成功，就将使我国成为世界上第三个将核动力应用于太空探测的国家。更多天文信息时刻关注@天文简报","createTime":"1384523369","info1":"","info2":"","info3":"","mlevel":"","musicurl":[],"pic_list":[],"praiseCount":"0","reportCount":"0","source":"三星Galaxy Note 10.1","userId":"fefec70500baee24b8f4f0449779404d","videourl":[],"weiboId":"929ce611e2ba1dc42acf045ea78b238a","weiboUrl":"05d293c464ba6927a9fb0b6068cb379c"}]
[{"beCommentWeiboId":"d41d8cd98f00b204e9800998ecf8427e","beForwardWeiboId":"d41d8cd98f00b204e9800998ecf8427e","catchTime":"1387807416","commentCount":"2","content":"#熟知天下#【嫦娥三号探测器将采用核动力推进技术不逊美国】我国嫦娥三号月球探测器发射在即，为能够在月球上过夜；嫦娥三号需要经受长时间严寒的挑战。为了突破这一难关，嫦娥三号将携带核能电池飞天。如能成功，将使我国成为继美俄之后，世界上第三个将核动力应用于太空探测国家。","createTime":"1384523159","info1":"","info2":"","info3":"","mlevel":"","musicurl":[],"pic_list":["http:\/\/ww3.sinaimg.cn\/thumbnail\/be78ae12gw1eam1hsfvpjj20ca08574w.jpg"],"praiseCount":"0","reportCount":"5","source":"专业版微博","userId":"544bca3072a002551ae18fdd1cb01ab2","videourl":[],"weiboId":"627d1610c655125bfccfa8098b07321d","weiboUrl":"f67ca1ce23a118e23ca3d4feeecc5faa"}]
[{"beCommentWeiboId":"d41d8cd98f00b204e9800998ecf8427e","beForwardWeiboId":"d41d8cd98f00b204e9800998ecf8427e","catchTime":"1387807416","commentCount":"0","content":"【嫦娥三号将登月北京园博会航天园成新热点】11月10日，北京园博会游人达到10.6万人，再创新高。航天园则成为园博园冬季游客的新热点。随着我国嫦娥三号登月探测器将在2013年底前月球软着陆和自动巡视勘察消息的发布，园博园航天园吸引了大批航天迷。","createTime":"1384522634","info1":"","info2":"","info3":"","mlevel":"","musicurl":[],"pic_list":["http:\/\/ww1.sinaimg.cn\/thumbnail\/bc09a3f5jw1eam18pcnf7j207n05fq34.jpg"],"praiseCount":"0","reportCount":"0","source":"vivo_Xplay","userId":"e380fb5a0604ba32f9066d70eca5a32f","videourl":[],"weiboId":"22a89a210a1cc510d3839f98f7470acc","weiboUrl":"8826ff03d24c6f158202694c9e7731d6"}]
[{"beCommentWeiboId":"d41d8cd98f00b204e9800998ecf8427e","beForwardWeiboId":"d41d8cd98f00b204e9800998ecf8427e","catchTime":"1387807416","commentCount":"0","content":"嫦娥三号探测器采用核动力推进代表世界最高水平【嫦娥三号探测器采用核动力推进代表世界最高水平】这是嫦娥三号月球探测器，包括着陆器和巡视器，是我国研制的首次在外天体实施软着陆的航天器http://t.cn/8DF8IuB","createTime":"1384522546","info1":"","info2":"","info3":"","mlevel":"","musicurl":[],"pic_list":[],"praiseCount":"0","reportCount":"0","source":"分享按钮","userId":"55bcf9c8186654965d2ff14b97d765bb","videourl":[],"weiboId":"f7621bbab4cfa409e5a6ab7dd97cdb40","weiboUrl":"51bf738b85dd9be4cc8466cfcec1d9f0"}]
[{"beCommentWeiboId":"d41d8cd98f00b204e9800998ecf8427e","beForwardWeiboId":"d41d8cd98f00b204e9800998ecf8427e","catchTime":"1387807416","commentCount":"0","content":"【中国月球基地：将就地取材远程操作机器人工作】今年年底，令人瞩目的嫦娥三号月球探测器即将发射升空，从而实现我国探月工程二期重要的软着陆任务。而就在近期举办的2013年中国国际工业博览会上，国产月球车的模型已经提前与公众见面了。事实分享自@凤凰网http://t.cn/8DF8hL2","createTime":"1384522119","info1":"","info2":"","info3":"","mlevel":"","musicurl":[],"pic_list":[],"praiseCount":"0","reportCount":"0","source":"分享按钮","userId":"8535e60af67d9ec70729c04ede2be3c9","videourl":[],"weiboId":"5d8021586ca0f5f79359048993189b95","weiboUrl":"f517f69d933af629d56ee001e7b21e99"}]
[{"beCommentWeiboId":"d41d8cd98f00b204e9800998ecf8427e","beForwardWeiboId":"d41d8cd98f00b204e9800998ecf8427e","catchTime":"1387807416","commentCount":"0","content":"【中国月球基地：将就地取材远程操作机器人工作】今年年底，令人瞩目的嫦娥三号月球探测器即将发射升空，从而实现我国探月工程二期重要的软着陆任务。而就在近期举办的2013年中国国际工业博览会上，国产月球车的模型已经提前与公众见面了。事实分享自@凤凰网http://t.cn/8DFQrC9","createTime":"1384521940","info1":"","info2":"","info3":"","mlevel":"","musicurl":[],"pic_list":[],"praiseCount":"0","reportCount":"0","source":"分享按钮","userId":"00f5f8c6e411b17915cbcea894cbd9b0","videourl":[],"weiboId":"a7e6e41addb5c843cb92e57985fcf901","weiboUrl":"a9a1c61459e4850fa1d797641d13e8b6"}]
[{"beCommentWeiboId":"d41d8cd98f00b204e9800998ecf8427e","beForwardWeiboId":"d41d8cd98f00b204e9800998ecf8427e","catchTime":"1387807416","commentCount":"0","content":"【嫦娥三号将登月北京园博会航天园成新热点】11月10日，北京园博会游人达到10.6万人，再创新高。航天园则成为园博园冬季游客的新热点。随着我国嫦娥三号登月探测器将在2013年底前月球软着陆和自动巡视勘察消息的发布，园博园航天园吸引了大批航天迷。","createTime":"1384521635","info1":"","info2":"","info3":"","mlevel":"","musicurl":[],"pic_list":["http:\/\/ww3.sinaimg.cn\/thumbnail\/c476e2bfjw1eam0rctqsuj207n05fq34.jpg"],"praiseCount":"0","reportCount":"0","source":"皮皮时光机","userId":"5eb8fe068b6aa90d5b2f62cdb8ac7c0f","videourl":[],"weiboId":"342aaa616010a54e8bb5b639d5cd4681","weiboUrl":"f364e9264e1bfc90a116812d623d2ecc"}]
[{"beCommentWeiboId":"d41d8cd98f00b204e9800998ecf8427e","beForwardWeiboId":"d41d8cd98f00b204e9800998ecf8427e","catchTime":"1387807416","commentCount":"0","content":"【中国月球基地：将就地取材远程操作机器人工作】今年年底，令人瞩目的嫦娥三号月球探测器即将发射升空，从而实现我国探月工程二期重要的软着陆任务。而就在近期举办的2013年中国国际工业博览会上，国产月球车的模型已经提前与公众见面了。事实分享自@凤凰网http://t.cn/8DFQ7eV","createTime":"1384521020","info1":"","info2":"","info3":"","mlevel":"","musicurl":[],"pic_list":[],"praiseCount":"0","reportCount":"0","source":"分享按钮","userId":"cc710303674379cd456eae85471ee63a","videourl":[],"weiboId":"bb950d5e93d2caac3bc75684885fb20c","weiboUrl":"9d653c4fabb2bba2622358c5bdeef36a"}]
[{"beCommentWeiboId":"d41d8cd98f00b204e9800998ecf8427e","beForwardWeiboId":"d41d8cd98f00b204e9800998ecf8427e","catchTime":"1387807416","commentCount":"0","content":"【中国月球基地：将就地取材远程操作机器人工作】今年年底，令人瞩目的嫦娥三号月球探测器即将发射升空，从而实现我国探月工程二期重要的软着陆任务。而就在近期举办的2013年中国国际工业博览会上，国产月球车的模型已经提前与公众见面了。事实分享自@凤凰网http://t.cn/8DFH3iy","createTime":"1384520720","info1":"","info2":"","info3":"","mlevel":"","musicurl":[],"pic_list":["http:\/\/ww3.sinaimg.cn\/thumbnail\/95eebdefjw1eam0bj2yamj20ci08b75a.jpg"],"praiseCount":"0","reportCount":"0","source":"分享按钮","userId":"90d866a83a24b481d73a87bb36ba327c","videourl":[],"weiboId":"6370d1056724cf2a308fb5e2b4663ba1","weiboUrl":"070c8325b368b756c6c9648aef0beb50"}]
[{"beCommentWeiboId":"d41d8cd98f00b204e9800998ecf8427e","beForwardWeiboId":"d41d8cd98f00b204e9800998ecf8427e","catchTime":"1387807416","commentCount":"0","content":"【嫦娥三号探测器将采用核动力推进技术不逊美国】11月15日，我国嫦娥三号月球探测器发射在即，为能够在月球上过夜；嫦娥三号需要长时间经受严寒带来极大挑战。为了突破这一难关，嫦娥三号，将携带核能电池飞天。如能成功，就将使我国成为继美俄之后，成为世界上第三个将核动力应用于太空探测国家。","createTime":"1384520638","info1":"","info2":"","info3":"","mlevel":"","musicurl":[],"pic_list":["http:\/\/ww1.sinaimg.cn\/thumbnail\/a2b1ac4ejw1eam0a2o0mcj20ca08574w.jpg"],"praiseCount":"0","reportCount":"1","source":"vivo_Xplay","userId":"20c35e786248d31bf570426bfb7f3324","videourl":[],"weiboId":"974c47f16eb153dfcc8bfc043adbbe48","weiboUrl":"1d78688f8e3e3b6c2415a766d4bbafeb"}]
