[{"beCommentWeiboId":"d41d8cd98f00b204e9800998ecf8427e","beForwardWeiboId":"d41d8cd98f00b204e9800998ecf8427e","catchTime":"1387807819","commentCount":"1","content":"2013年11月11日，在这个奇妙的日子里，西安工业大学大学生科学技术协会科普部和办公室联合在经纬广场上进行宇航系列活动之嫦娥三号的科普活动，通过模型展出以及多彩的展板向全体大学生介绍我国的航天事业，使大家开阔视野、丰富自我。活动还在进行中欢迎大家参与，我们有人员讲解哦@西安工业大学团委","createTime":"1384233615","info1":"","info2":"","info3":"","mlevel":"","musicurl":[],"pic_list":["http:\/\/ww3.sinaimg.cn\/thumbnail\/772e40efjw1eai60kjqx5j202302st8j.jpg"],"praiseCount":"0","reportCount":"3","source":"新浪微博","userId":"63ae335a453088f25303293bf0d8fc54","videourl":[],"weiboId":"a387d52c2b70d2483d13ab05b45afdcb","weiboUrl":"7faee47acdcc68b22ea663716aaebeb9"}]
[{"beCommentWeiboId":"d41d8cd98f00b204e9800998ecf8427e","beForwardWeiboId":"d41d8cd98f00b204e9800998ecf8427e","catchTime":"1387807819","commentCount":"0","content":"帮姐转：邓老凉茶杯嫦娥三号月球车全球征名活动评审会终审。玉兔号、钱学森号、揽月号寻梦号、前进号、探索号、追梦号、梦想号、追月号、使命号十选三，哪个名字可以入围？转发并@十个好友，即可获赠邓老凉茶限量探月凉茶1罐。并有机会抽取月球车模型。#邓老凉茶约你一起去探月#更多精彩敬请关注。","createTime":"1384232934","info1":"","info2":"","info3":"","mlevel":"","musicurl":[],"pic_list":["http:\/\/ww2.sinaimg.cn\/square\/738daf68jw1eai5ok66igj20fj0qowgh.jpg"],"praiseCount":"0","reportCount":"1","source":"iPhone客户端","userId":"60d01a5692c1418aab1f9b0d807df6bd","videourl":[],"weiboId":"f14d67d3b8e6e08ca9c1229cd9b46e53","weiboUrl":"59cb044c104b860c171b46369433a514"}]
