[{"beCommentWeiboId":"d41d8cd98f00b204e9800998ecf8427e","beForwardWeiboId":"d41d8cd98f00b204e9800998ecf8427e","catchTime":"1387807876","commentCount":"0","content":"嫦娥三号探测器将采用核动力推进技术不逊美国http://t.cn/8Dkqng6","createTime":"1384484265","info1":"","info2":"","info3":"","mlevel":"","musicurl":[],"pic_list":[],"praiseCount":"0","reportCount":"0","source":"Android客户端","userId":"ad370c4f16d05fa2ba11c0fc3e5ce697","videourl":[],"weiboId":"8dd46516104d76bf6bf727a6bca513dd","weiboUrl":"be339e58946c97048bb2b1984f14d87d"}]
[{"beCommentWeiboId":"d41d8cd98f00b204e9800998ecf8427e","beForwardWeiboId":"d41d8cd98f00b204e9800998ecf8427e","catchTime":"1387807876","commentCount":"0","content":"【嫦娥三号探测器将采用核动力推进技术不逊美国】11月15日，我国嫦娥三号月球探测器发射在即，为能够在月球上过夜；嫦娥三号需要长时间经受严寒带来极大挑战。为了突破这一难关，嫦娥三号，将携带核能电池飞天。如能成功，就将使我国成为继美俄之后，成为世界上第三个将核动力应用于太空探测国家。","createTime":"1384484206","info1":"","info2":"","info3":"","mlevel":"","musicurl":[],"pic_list":["http:\/\/ww3.sinaimg.cn\/thumbnail\/d8de7f5ejw1ealiqar5hij20ca08574w.jpg"],"praiseCount":"0","reportCount":"0","source":"皮皮时光机","userId":"0ed4e44dd0d50ecb6dfdc908d920b0c2","videourl":[],"weiboId":"2019dd939cc8e24df4b541190fdea7a0","weiboUrl":"616337cfb7f682e199b4148c716fb1b5"}]
[{"beCommentWeiboId":"d41d8cd98f00b204e9800998ecf8427e","beForwardWeiboId":"d41d8cd98f00b204e9800998ecf8427e","catchTime":"1387807876","commentCount":"1","content":"嫦娥奔月航天科技北京有限公司以下简称嫦娥公司与北京华信新业文化发展有限公司以下简称北京华信新业公司在京签署了&quot;中国探月&quot;玉石类纪念藏品独家授权签约仪式。这意味着，在&quot;嫦娥三号&quot;即将发射之际，又一铭刻和见证中国探月与航天事业辉煌成就的珍贵文化藏品即将面世。","createTime":"1384484177","info1":"","info2":"","info3":"","mlevel":"","musicurl":[],"pic_list":["http:\/\/ww4.sinaimg.cn\/thumbnail\/831f854agw1ealipqsg9pj20dw0jnjt2.jpg"],"praiseCount":"0","reportCount":"2","source":"新浪微博","userId":"4fb884b41b88616e7e7d3425a52f7d14","videourl":[],"weiboId":"a2accb09ea376b24a0c169b0606d0f2b","weiboUrl":"59ac7d19f31a0e57052cd7a5f54234f1"}]
[{"beCommentWeiboId":"d41d8cd98f00b204e9800998ecf8427e","beForwardWeiboId":"d41d8cd98f00b204e9800998ecf8427e","catchTime":"1387807876","commentCount":"0","content":"【嫦娥三号探测器将采用核动力推进技术不逊美国】11月15日，我国嫦娥三号月球探测器发射在即，为能够在月球上过夜；嫦娥三号需要长时间经受严寒带来极大挑战。为了突破这一难关，嫦娥三号，将携带核能电池飞天。如能成功，就将使我国成为继美俄之后，成为世界上第三个将核动力应用于太空探测国家。","createTime":"1384484138","info1":"","info2":"","info3":"","mlevel":"","musicurl":[],"pic_list":["http:\/\/ww3.sinaimg.cn\/thumbnail\/7e75b76fjw1ealip46h67j20ca0843zp.jpg"],"praiseCount":"0","reportCount":"1","source":"雷曼克斯科技有限公司","userId":"59e159216d45a0146c2959caa8ffc475","videourl":[],"weiboId":"0d442224dd7a695823c139d5ac64e8fd","weiboUrl":"93670ffb864c9d41dcbdcd14b03f3af4"}]
[{"beCommentWeiboId":"d41d8cd98f00b204e9800998ecf8427e","beForwardWeiboId":"d41d8cd98f00b204e9800998ecf8427e","catchTime":"1387807876","commentCount":"0","content":"嫦娥三号探测器将采用核动力推进技术不逊美国—新闻—科学网http://t.cn/8DFLFjP","createTime":"1384484131","info1":"","info2":"","info3":"","mlevel":"","musicurl":[],"pic_list":["http:\/\/ww4.sinaimg.cn\/thumbnail\/8093aff3jw1ealioyufqxj20ci08b75a.jpg"],"praiseCount":"0","reportCount":"0","source":"加网分享按钮","userId":"806deb66be09e47dedba5f1ec7293af8","videourl":[],"weiboId":"1537e554727f532585be2ed78d826319","weiboUrl":"7e5f7aea21139951a6913bf8b88911cd"}]
[{"beCommentWeiboId":"d41d8cd98f00b204e9800998ecf8427e","beForwardWeiboId":"d41d8cd98f00b204e9800998ecf8427e","catchTime":"1387807876","commentCount":"0","content":"【嫦娥三号探测器将采用核动力推进技术不逊美国】11月15日，我国嫦娥三号月球探测器发射在即，为能够在月球上过夜；嫦娥三号需要长时间经受严寒带来极大挑战。为了突破这一难关，嫦娥三号，将携带核能电池飞天。如能成功，就将使我国成为继美俄之后，成为世界上第三个将核动力应用于太空探测国家。","createTime":"1384484076","info1":"","info2":"","info3":"","mlevel":"","musicurl":[],"pic_list":["http:\/\/ww4.sinaimg.cn\/thumbnail\/e569950ejw1ealio0wmawj20ca08574w.jpg"],"praiseCount":"0","reportCount":"0","source":"vivo_Xplay","userId":"2a5cbc6f9e6a12c9ce5d03101ed82c7e","videourl":[],"weiboId":"e8a5ea09d2c47d96eb8e4a106b45a221","weiboUrl":"e7701e68116c02ce29049c067582192c"}]
[{"beCommentWeiboId":"d41d8cd98f00b204e9800998ecf8427e","beForwardWeiboId":"d41d8cd98f00b204e9800998ecf8427e","catchTime":"1387807876","commentCount":"0","content":"【嫦娥三号探测器将采用核动力推进技术不逊美国】11月15日，我国嫦娥三号月球探测器发射在即，为能够在月球上过夜；嫦娥三号需要长时间经受严寒带来极大挑战。为了突破这一难关，嫦娥三号，将携带核能电池飞天。如能成功，就将使我国成为继美俄之后，成为世界上第三个将核动力应用于太空探测国家。","createTime":"1384483962","info1":"","info2":"","info3":"","mlevel":"","musicurl":[],"pic_list":["http:\/\/ww4.sinaimg.cn\/thumbnail\/e5cde113jw1ealim2sukzj20ca08574w.jpg"],"praiseCount":"0","reportCount":"0","source":"vivo_Xplay","userId":"2eb9588a399dfb9427f809980c9c89e9","videourl":[],"weiboId":"4694576ed44eb16c89b101a834a3fc16","weiboUrl":"1aab7b3d98a965e4fbe8e74ec7e467b9"}]
[{"beCommentWeiboId":"d41d8cd98f00b204e9800998ecf8427e","beForwardWeiboId":"d41d8cd98f00b204e9800998ecf8427e","catchTime":"1387807876","commentCount":"47","content":"【嫦娥三号探测器将采用核动力推进】我国嫦娥三号月球探测器发射在即，为了能够在月球上过夜；嫦娥三号需要长时间经受严寒带来的极大挑战。为了突破这一难关，我国嫦娥三号，将携带核能电池飞天。如能成功，我国将成继美俄之后，成为世界上第三个将核动力应用于太空探测的国家。http://t.cn/8Dkqng6","createTime":"1384424094","info1":"","info2":"","info3":"","mlevel":"","musicurl":[],"pic_list":["http:\/\/ww1.sinaimg.cn\/thumbnail\/61e895aejw1eakprtt1drj20ci08b75a.jpg"],"praiseCount":"","reportCount":"147","source":"新浪微博","userId":"447a585357daff81f574a55e3c857bdf","videourl":[],"weiboId":"f8dd740f97523ecf9a2ae7ba58c679c9","weiboUrl":"695619124595ebed7df112569c25b508"}]
[{"beCommentWeiboId":"d41d8cd98f00b204e9800998ecf8427e","beForwardWeiboId":"f8dd740f97523ecf9a2ae7ba58c679c9","catchTime":"1387807876","commentCount":"0","content":"//@吉尔阿作://@西昌同城会:即将在西昌卫星中心发射的嫦娥三号，将携带核能电池飞天，如能成功，我国将成继美俄之后，成为世界上第三个将核动力应用于太空探测的国家。","createTime":"1384483800","info1":"","info2":"","info3":"","mlevel":"","musicurl":[],"pic_list":[],"praiseCount":"0","reportCount":"0","source":"新浪微博","userId":"b08430fc79d68d0309734e97347b02c7","videourl":[],"weiboId":"80cdd9ecf63eb5c324f2f235dc7fe24d","weiboUrl":"4d21f93642c1ab38751c6d1c122683f8"}]
[{"beCommentWeiboId":"d41d8cd98f00b204e9800998ecf8427e","beForwardWeiboId":"d41d8cd98f00b204e9800998ecf8427e","catchTime":"1387807876","commentCount":"0","content":"【嫦娥三号探测器将采用核动力推进技术不逊美国】11月15日，我国嫦娥三号月球探测器发射在即，为能够在月球上过夜；嫦娥三号需要长时间经受严寒带来极大挑战。为了突破这一难关，嫦娥三号，将携带核能电池飞天。如能成功，就将使我国成为继美俄之后，成为世界上第三个将核动力应用于太空探测国家。","createTime":"1384483699","info1":"","info2":"","info3":"","mlevel":"","musicurl":[],"pic_list":["http:\/\/ww1.sinaimg.cn\/thumbnail\/e7a6403bjw1ealihh7021j20ca08574w.jpg"],"praiseCount":"0","reportCount":"0","source":"皮皮时光机","userId":"fd4936a7cfc7cec9090aa3cf35703639","videourl":[],"weiboId":"b062d211144de487223c678ee1924699","weiboUrl":"41c3f5ffe79073ad5e6b1cb4fa322608"}]
[{"beCommentWeiboId":"d41d8cd98f00b204e9800998ecf8427e","beForwardWeiboId":"d41d8cd98f00b204e9800998ecf8427e","catchTime":"1387807876","commentCount":"0","content":"【嫦娥三号探测器将采用核动力推进技术不逊美国】11月15日，我国嫦娥三号月球探测器发射在即，为能够在月球上过夜；嫦娥三号需要长时间经受严寒带来极大挑战。为了突破这一难关，嫦娥三号，将携带核能电池飞天。如能成功，就将使我国成为继美俄之后，成为世界上第三个将核动力应用于太空探测国家。","createTime":"1384483659","info1":"","info2":"","info3":"","mlevel":"","musicurl":[],"pic_list":["http:\/\/ww3.sinaimg.cn\/thumbnail\/e45f0cf4jw1ealigt5jufj20ca08574w.jpg"],"praiseCount":"0","reportCount":"0","source":"vivo_Xplay","userId":"5f1e3fe2c928566e42b052e1f2f20c8a","videourl":[],"weiboId":"0d3773a405358bcc13cc7b6fe38c6742","weiboUrl":"9bfc7efca458427660f4ee7339d1d61d"}]
[{"beCommentWeiboId":"d41d8cd98f00b204e9800998ecf8427e","beForwardWeiboId":"d41d8cd98f00b204e9800998ecf8427e","catchTime":"1387807876","commentCount":"0","content":"【嫦娥三号探测器采用核动力推进代表世界最高水平】这是嫦娥三号月球探测器，包括着陆器和巡视器，是我国研制的首次在外天体实施软着陆的航天器。图片来源：新华社)我国嫦娥三号月球探测器发射在即，为了能够在月球上过夜;嫦娥三号需要长时间经分享自@凤凰网http://t.cn/8DFLoXg","createTime":"1384483645","info1":"","info2":"","info3":"","mlevel":"","musicurl":[],"pic_list":["http:\/\/ww2.sinaimg.cn\/thumbnail\/9d709375jw1ealigke4ipj20ci08b75a.jpg"],"praiseCount":"0","reportCount":"0","source":"分享按钮","userId":"b879cb51ab92f0ab88ae132cf36a7e4e","videourl":[],"weiboId":"0145abef6e25e749c21dc9d19e292806","weiboUrl":"6d3fe6e1a6ed22276eae56046c461ba8"}]
[{"beCommentWeiboId":"d41d8cd98f00b204e9800998ecf8427e","beForwardWeiboId":"d41d8cd98f00b204e9800998ecf8427e","catchTime":"1387807876","commentCount":"0","content":"【嫦娥三号探测器将采用核动力推进技术不逊美国】11月15日，我国嫦娥三号月球探测器发射在即，为能够在月球上过夜；嫦娥三号需要长时间经受严寒带来极大挑战。为了突破这一难关，嫦娥三号，将携带核能电池飞天。如能成功，就将使我国成为继美俄之后，成为世界上第三个将核动力应用于太空探测国家。","createTime":"1384483584","info1":"","info2":"","info3":"","mlevel":"","musicurl":[],"pic_list":["http:\/\/ww2.sinaimg.cn\/thumbnail\/9ba9d910jw1ealifh4zipj20ca08574w.jpg"],"praiseCount":"0","reportCount":"0","source":"皮皮时光机","userId":"b3a8553bb4049920c830f49dc1b6eecd","videourl":[],"weiboId":"510bcec21f319210c225cc34faf96008","weiboUrl":"d22a05f3cd2a0b5f5117178f648a65ea"}]
[{"beCommentWeiboId":"d41d8cd98f00b204e9800998ecf8427e","beForwardWeiboId":"d41d8cd98f00b204e9800998ecf8427e","catchTime":"1387807876","commentCount":"0","content":"【嫦娥三号探测器将采用核动力推进技术不逊美国】11月15日，我国嫦娥三号月球探测器发射在即，为能够在月球上过夜；嫦娥三号需要长时间经受严寒带来极大挑战。为了突破这一难关，嫦娥三号，将携带核能电池飞天。如能成功，就将使我国成为继美俄之后，成为世界上第三个将核动力应用于太空探测国家。","createTime":"1384483584","info1":"","info2":"","info3":"","mlevel":"","musicurl":[],"pic_list":["http:\/\/ww1.sinaimg.cn\/thumbnail\/7e44a835jw1ealifhj90gj20ca08574w.jpg"],"praiseCount":"0","reportCount":"1","source":"皮皮时光机","userId":"23e3a0c78f483f95d727a6f3ba647c07","videourl":[],"weiboId":"25a72841c536873ccb7f2b129de669e3","weiboUrl":"2fb10cc7f5e8b7ba36a0d0a191ba4f61"}]
[{"beCommentWeiboId":"d41d8cd98f00b204e9800998ecf8427e","beForwardWeiboId":"d41d8cd98f00b204e9800998ecf8427e","catchTime":"1387807876","commentCount":"0","content":"涉及探测器以及嫦娥三号发射问题，在航天吧问，特别有效果_月球吧_百度贴吧http://t.cn/8DFLMFu","createTime":"1384483536","info1":"","info2":"","info3":"","mlevel":"","musicurl":[],"pic_list":["http:\/\/ww1.sinaimg.cn\/thumbnail\/613de4e1jw1ealien5z5fj2032032weg.jpg"],"praiseCount":"0","reportCount":"0","source":"百度贴吧","userId":"8a74e8f02724fe810e0eb0251695e41b","videourl":[],"weiboId":"1783b83664462aa2ea7f5716fec368ca","weiboUrl":"90c30d582ba4250293d3cfde852f75f4"}]
[{"beCommentWeiboId":"d41d8cd98f00b204e9800998ecf8427e","beForwardWeiboId":"d41d8cd98f00b204e9800998ecf8427e","catchTime":"1387807876","commentCount":"0","content":"【嫦娥三号“月球车”原理样机将亮相上海工博会】2013年中国国际工业博览会将于11月5日至9日在上海新国际博览中心举行。由科技部和上海市科委组织的“创新科技馆”将展出多种具有自主知识产权高端、高效、高附加值和低消耗的先进制造技术与产品，其中将于今年年底登陆月球的“月球车”模型将首次亮相。","createTime":"1384483500","info1":"","info2":"","info3":"","mlevel":"","musicurl":[],"pic_list":["http:\/\/ww3.sinaimg.cn\/thumbnail\/e5b3c0d3jw1ealie12xtlj20a40an0t4.jpg"],"praiseCount":"0","reportCount":"0","source":"vivo_Xplay","userId":"377c078bacbb6240059c1cd0bb356ffc","videourl":[],"weiboId":"fbfcfc0f41cfef03a590a48ad14e4493","weiboUrl":"0fbe7e6e90684cf3af9a4b74a27c26e3"}]
[{"beCommentWeiboId":"d41d8cd98f00b204e9800998ecf8427e","beForwardWeiboId":"d41d8cd98f00b204e9800998ecf8427e","catchTime":"1387807876","commentCount":"0","content":"【嫦娥三号探测器将采用核动力推进技术不逊美国】11月15日，我国嫦娥三号月球探测器发射在即，为能够在月球上过夜；嫦娥三号需要长时间经受严寒带来极大挑战。为了突破这一难关，嫦娥三号，将携带核能电池飞天。如能成功，就将使我国成为继美俄之后，成为世界上第三个将核动力应用于太空探测国家。","createTime":"1384483500","info1":"","info2":"","info3":"","mlevel":"","musicurl":[],"pic_list":["http:\/\/ww2.sinaimg.cn\/thumbnail\/e0652dfejw1ealie0zimxj20ca08574w.jpg"],"praiseCount":"0","reportCount":"0","source":"vivo_Xplay","userId":"a4bb4376d0b8b177648c0637c86d6cbf","videourl":[],"weiboId":"19af3c1dd9ef5dc2ad5cec2dead2fb38","weiboUrl":"ba0a8b17f9bf86a04990873b78a7494f"}]
[{"beCommentWeiboId":"d41d8cd98f00b204e9800998ecf8427e","beForwardWeiboId":"d41d8cd98f00b204e9800998ecf8427e","catchTime":"1387807876","commentCount":"0","content":"【嫦娥三号探测器将采用核动力推进技术不逊美国】11月15日，我国嫦娥三号月球探测器发射在即，为能够在月球上过夜；嫦娥三号需要长时间经受严寒带来极大挑战。为了突破这一难关，嫦娥三号，将携带核能电池飞天。如能成功，就将使我国成为继美俄之后，成为世界上第三个将核动力应用于太空探测国家。","createTime":"1384483461","info1":"","info2":"","info3":"","mlevel":"","musicurl":[],"pic_list":["http:\/\/ww2.sinaimg.cn\/thumbnail\/e3b9c791jw1ealidd9a88j20ca08574w.jpg"],"praiseCount":"0","reportCount":"0","source":"vivo_Xplay","userId":"be28331363c934ca2bf6e830deec0d81","videourl":[],"weiboId":"c0ae467075600b6507beede0a71f708d","weiboUrl":"cf99bff7857a50b2c406b27e752e6b03"}]
[{"beCommentWeiboId":"d41d8cd98f00b204e9800998ecf8427e","beForwardWeiboId":"d41d8cd98f00b204e9800998ecf8427e","catchTime":"1387807876","commentCount":"0","content":"嫦娥三号探测器将采用核动力推进技术不逊美国分享自@新浪军事http://t.cn/8DFLqzV","createTime":"1384483416","info1":"","info2":"","info3":"","mlevel":"","musicurl":[],"pic_list":["http:\/\/ww4.sinaimg.cn\/thumbnail\/45af7a54jw1ealicklbamj20ci08b75a.jpg"],"praiseCount":"0","reportCount":"0","source":"新浪军事","userId":"78377b561133a1933a292233047f4b44","videourl":[],"weiboId":"07f70c0af4474247dba7a8a35d8ed616","weiboUrl":"53a8b11159ec55463aadb361cf5df366"}]
[{"beCommentWeiboId":"d41d8cd98f00b204e9800998ecf8427e","beForwardWeiboId":"d41d8cd98f00b204e9800998ecf8427e","catchTime":"1387807876","commentCount":"14","content":"今天应该买什么票？核动力能源的嫦娥三号预定12月2日发射，必定会有媒体大面积报道，引发新闻资讯共振是大概率，所以，当前可积极关注核能概念","createTime":"1384483363","info1":"","info2":"","info3":"","mlevel":"","musicurl":[],"pic_list":[],"praiseCount":"0","reportCount":"10","source":"新浪微博","userId":"619aed2c9caf341d0b723da764246830","videourl":[],"weiboId":"32f658a02b4fb8c5da502e01ff09c728","weiboUrl":"e5095d020c515478a9348e72682fb3ba"}]
[{"beCommentWeiboId":"d41d8cd98f00b204e9800998ecf8427e","beForwardWeiboId":"d41d8cd98f00b204e9800998ecf8427e","catchTime":"1387807877","commentCount":"0","content":"【嫦娥三号探测器采用核动力推进代表世界最高水平】这是嫦娥三号月球探测器，包括着陆器和巡视器，是我国研制的首次在外天体实施软着陆的航天器。图片来源：新华社)我国嫦娥三号月球探测器发射在即，为了能够在月球上过夜;嫦娥三号需要长时间经分享自@凤凰网http://t.cn/8DFLL4B","createTime":"1384483319","info1":"","info2":"","info3":"","mlevel":"","musicurl":[],"pic_list":["http:\/\/ww2.sinaimg.cn\/thumbnail\/887936a5jw1ealiawhjafj20ci08b75a.jpg"],"praiseCount":"0","reportCount":"0","source":"分享按钮","userId":"3b21294d873de5455904805e550c9f05","videourl":[],"weiboId":"ac3dada576e625a9aa57d490805e996d","weiboUrl":"29c38242cc4e00c013b8ab35b82cec06"}]
[{"beCommentWeiboId":"d41d8cd98f00b204e9800998ecf8427e","beForwardWeiboId":"d41d8cd98f00b204e9800998ecf8427e","catchTime":"1387807877","commentCount":"0","content":"赶紧发明核手机电池吧！以后手机都不用充电啦！《嫦娥三号将采用核动力推进》(来自@新浪科技)http://t.cn/8Dkqng6","createTime":"1384483254","info1":"","info2":"","info3":"","mlevel":"","musicurl":[],"pic_list":["http:\/\/ww4.sinaimg.cn\/thumbnail\/d0c01741jw1eali9s20prj20ci08b75a.jpg"],"praiseCount":"0","reportCount":"0","source":"手机新浪网","userId":"c1b347fad10a78cacaf72a89ec104294","videourl":[],"weiboId":"82a216c592ec834eaaa7865096feb516","weiboUrl":"ca50d79ee1228a8fdd7976df7969976a"}]
[{"beCommentWeiboId":"d41d8cd98f00b204e9800998ecf8427e","beForwardWeiboId":"d41d8cd98f00b204e9800998ecf8427e","catchTime":"1387807877","commentCount":"0","content":"【嫦娥三号探测器将采用核动力推进技术不逊美国】11月15日，我国嫦娥三号月球探测器发射在即，为能够在月球上过夜；嫦娥三号需要长时间经受严寒带来极大挑战。为了突破这一难关，嫦娥三号，将携带核能电池飞天。如能成功，就将使我国成为继美俄之后，成为世界上第三个将核动力应用于太空探测国家。","createTime":"1384483097","info1":"","info2":"","info3":"","mlevel":"","musicurl":[],"pic_list":["http:\/\/ww3.sinaimg.cn\/thumbnail\/6ebbb3b9jw1eali71nd5gj20ca08574w.jpg"],"praiseCount":"0","reportCount":"0","source":"vivo_Xplay","userId":"809bf84c5446fe2b36813118d72e841d","videourl":[],"weiboId":"44e306a1379a4eec36b0eadce716a214","weiboUrl":"2cde5ab3a5aaa6cfb6a4f0671f3aa64d"}]
[{"beCommentWeiboId":"d41d8cd98f00b204e9800998ecf8427e","beForwardWeiboId":"d41d8cd98f00b204e9800998ecf8427e","catchTime":"1387807877","commentCount":"0","content":"民营配套单位发挥自身优势积极参与嫦娥三号任务新闻频道和讯网http://t.cn/8DF2rb2","createTime":"1384483062","info1":"","info2":"","info3":"","mlevel":"","musicurl":[],"pic_list":[],"praiseCount":"0","reportCount":"0","source":"百度分享","userId":"8a74e8f02724fe810e0eb0251695e41b","videourl":[],"weiboId":"4de149a7de83545ed6714203b829bb2d","weiboUrl":"adddba4e7daaa465cbb96da6b33ca954"}]
[{"beCommentWeiboId":"d41d8cd98f00b204e9800998ecf8427e","beForwardWeiboId":"d41d8cd98f00b204e9800998ecf8427e","catchTime":"1387807877","commentCount":"0","content":"【嫦娥三号探测器将采用核动力推进技术不逊美国】11月15日，我国嫦娥三号月球探测器发射在即，为能够在月球上过夜；嫦娥三号需要长时间经受严寒带来极大挑战。为了突破这一难关，嫦娥三号，将携带核能电池飞天。如能成功，就将使我国成为继美俄之后，成为世界上第三个将核动力应用于太空探测国家。","createTime":"1384483042","info1":"","info2":"","info3":"","mlevel":"","musicurl":[],"pic_list":["http:\/\/ww2.sinaimg.cn\/thumbnail\/e5b3c0d6jw1eali63n1qgj20ca08574w.jpg"],"praiseCount":"0","reportCount":"0","source":"vivo_Xplay","userId":"fd68b81413528f9db442d30cf4526c1c","videourl":[],"weiboId":"ece7fffa9389a1d14ae4714b7f9591d3","weiboUrl":"09fbed5805a59f41a62a0cbc6cb3ac06"}]
[{"beCommentWeiboId":"d41d8cd98f00b204e9800998ecf8427e","beForwardWeiboId":"d41d8cd98f00b204e9800998ecf8427e","catchTime":"1387807877","commentCount":"0","content":"【嫦娥三号探测器将采用核动力推进技术不逊美国】11月15日，我国嫦娥三号月球探测器发射在即，为能够在月球上过夜；嫦娥三号需要长时间经受严寒带来极大挑战。为了突破这一难关，嫦娥三号，将携带核能电池飞天。如能成功，就将使我国成为继美俄之后，成为世界上第三个将核动力应用于太空探测国家。","createTime":"1384483041","info1":"","info2":"","info3":"","mlevel":"","musicurl":[],"pic_list":["http:\/\/ww2.sinaimg.cn\/thumbnail\/d40c452bjw1eali63b14sj20ca08574w.jpg"],"praiseCount":"0","reportCount":"0","source":"皮皮时光机","userId":"75b7c7bca6bdf657784d9b2e375791eb","videourl":[],"weiboId":"4e8354545c1900f2422c231f0d045f34","weiboUrl":"9873790f5cb28973b2b7ca0cecb9b67f"}]
[{"beCommentWeiboId":"d41d8cd98f00b204e9800998ecf8427e","beForwardWeiboId":"d41d8cd98f00b204e9800998ecf8427e","catchTime":"1387807877","commentCount":"0","content":"、11月15日，我国嫦娥三号月球探测器发射在即，为能够在月球上过夜；嫦娥三号需要长时间经受严寒带来极大挑战。为了突破这一难关，嫦娥三号，将携带核能电池飞天。如能成功，就将使我国成为继美俄之后，成为世界上第三个将核动力应用于太空探测国家。","createTime":"1384482798","info1":"","info2":"","info3":"","mlevel":"","musicurl":[],"pic_list":["http:\/\/ww4.sinaimg.cn\/thumbnail\/7eff6d91jw1eali1uo3qnj20ca08574w.jpg"],"praiseCount":"0","reportCount":"0","source":"北京新华电脑学校官网","userId":"14f7098836d81859c75a4fdf3fb04b8f","videourl":[],"weiboId":"c4f7391ee8e2d4afbde7ac6fc6eebb87","weiboUrl":"0913cb40ed0468bb832731d4986f7701"}]
[{"beCommentWeiboId":"d41d8cd98f00b204e9800998ecf8427e","beForwardWeiboId":"d41d8cd98f00b204e9800998ecf8427e","catchTime":"1387807877","commentCount":"0","content":"【嫦娥三号探测器将采用核动力推进技术不逊美国】11月15日，我国嫦娥三号月球探测器发射在即，为能够在月球上过夜；嫦娥三号需要长时间经受严寒带来极大挑战。为了突破这一难关，嫦娥三号，将携带核能电池飞天。如能成功，就将使我国成为继美俄之后，成为世界上第三个将核动力应用于太空探测国家。","createTime":"1384482684","info1":"","info2":"","info3":"","mlevel":"","musicurl":[],"pic_list":["http:\/\/ww3.sinaimg.cn\/thumbnail\/c39a5ca8jw1ealhzw103cj20ca08574w.jpg"],"praiseCount":"0","reportCount":"0","source":"皮皮时光机","userId":"fe92fe45db6c8cbf2f086c589c2638b7","videourl":[],"weiboId":"8109c9c24ec854d9da0b31a168038679","weiboUrl":"ceaf4213b1a604af513cfaadf281507b"}]
[{"beCommentWeiboId":"d41d8cd98f00b204e9800998ecf8427e","beForwardWeiboId":"d41d8cd98f00b204e9800998ecf8427e","catchTime":"1387807877","commentCount":"0","content":"【嫦娥三号探测器将采用核动力推进技术不逊美国】11月15日，我国嫦娥三号月球探测器发射在即，为能够在月球上过夜；嫦娥三号需要长时间经受严寒带来极大挑战。为了突破这一难关，嫦娥三号，将携带核能电池飞天。如能成功，就将使我国成为继美俄之后，成为世界上第三个将核动力应用于太空探测国家。","createTime":"1384482618","info1":"","info2":"","info3":"","mlevel":"","musicurl":[],"pic_list":["http:\/\/ww1.sinaimg.cn\/thumbnail\/74baa7e9jw1ealhyr1rbrj20ca08574w.jpg"],"praiseCount":"0","reportCount":"0","source":"皮皮时光机","userId":"68f8beb7be6111b1e2bf08fae7633a96","videourl":[],"weiboId":"704d9301366e0deb8c21e594a038b156","weiboUrl":"937a320d34eb5aea434bafdafe366c6f"}]
[{"beCommentWeiboId":"d41d8cd98f00b204e9800998ecf8427e","beForwardWeiboId":"d41d8cd98f00b204e9800998ecf8427e","catchTime":"1387807877","commentCount":"0","content":"嫦娥三号核能电池探测器真正的核电池概念股龙头股是哪些_钱聚网_股票入门|股票基础知识|股票入门基础知识http://t.cn/8DF2boY","createTime":"1384482449","info1":"","info2":"","info3":"","mlevel":"","musicurl":[],"pic_list":[],"praiseCount":"0","reportCount":"0","source":"百度分享","userId":"9200004dfd4e87b29f088f1671b49cba","videourl":[],"weiboId":"156ca5478606d0a1b5568804b65b9af5","weiboUrl":"f0d0eb0c36f77cb3e822718b098555fd"}]
[{"beCommentWeiboId":"d41d8cd98f00b204e9800998ecf8427e","beForwardWeiboId":"d41d8cd98f00b204e9800998ecf8427e","catchTime":"1387807877","commentCount":"0","content":"发表了博文《嫦娥三号探测器将采用核动力推进技术不逊美国》嫦娥三号探测器将采用核动力推进技术不逊美国2013111417:38来源：人民网1人参与1条评论字号：小中大http://t.cn/8DF2LfN","createTime":"1384482381","info1":"","info2":"","info3":"","mlevel":"","musicurl":[],"pic_list":[],"praiseCount":"0","reportCount":"0","source":"新浪博客","userId":"c1efe85b633351b71e9ede043588aff9","videourl":[],"weiboId":"92f74fbdb4732574c43c1a07f789af6c","weiboUrl":"53b3a889fa8cd7cb89348094187c3fbc"}]
[{"beCommentWeiboId":"d41d8cd98f00b204e9800998ecf8427e","beForwardWeiboId":"d41d8cd98f00b204e9800998ecf8427e","catchTime":"1387807877","commentCount":"0","content":"【嫦娥三号探测器采用核动力推进代表世界最高水平】这是嫦娥三号月球探测器，包括着陆器和巡视器，是我国研制的首次在外天体实施软着陆的航天器。图片来源：新华社)我国嫦娥三号月球探测器发射在即，为了能够在月球上过夜;嫦娥三号需要长时间经http://t.cn/8DF2wei","createTime":"1384482351","info1":"","info2":"","info3":"","mlevel":"","musicurl":[],"pic_list":[],"praiseCount":"0","reportCount":"0","source":"分享按钮","userId":"9110a778706654d4a062345c9f3a3b49","videourl":[],"weiboId":"51cb9cc8562819666a3264802678ca0e","weiboUrl":"bcb3abc28eb0bcf415957b075e639776"}]
[{"beCommentWeiboId":"d41d8cd98f00b204e9800998ecf8427e","beForwardWeiboId":"d41d8cd98f00b204e9800998ecf8427e","catchTime":"1387807877","commentCount":"0","content":"【嫦娥三号探测器将采用核动力推进技术不逊美国】11月15日，我国嫦娥三号月球探测器发射在即，为能够在月球上过夜；嫦娥三号需要长时间经受严寒带来极大挑战。为了突破这一难关，嫦娥三号，将携带核能电池飞天。如能成功，就将使我国成为继美俄之后，成为世界上第三个将核动力应用于太空探测国家。","createTime":"1384482280","info1":"","info2":"","info3":"","mlevel":"","musicurl":[],"pic_list":["http:\/\/ww1.sinaimg.cn\/thumbnail\/d8dcffc4jw1ealhsvkrrfj20ca08574w.jpg"],"praiseCount":"0","reportCount":"0","source":"皮皮时光机","userId":"08e95f228dd880cba0f413cc03355119","videourl":[],"weiboId":"f1226696577e315d6533d8f29dd4d8ef","weiboUrl":"373a6ee357dc801d423263695a09d3c5"}]
[{"beCommentWeiboId":"d41d8cd98f00b204e9800998ecf8427e","beForwardWeiboId":"d41d8cd98f00b204e9800998ecf8427e","catchTime":"1387807877","commentCount":"0","content":"【嫦娥三号探测器将采用核动力推进技术不逊美国】11月15日，我国嫦娥三号月球探测器发射在即，为能够在月球上过夜；嫦娥三号需要长时间经受严寒带来极大挑战。为了突破这一难关，嫦娥三号，将携带核能电池飞天。如能成功，就将使我国成为继美俄之后，成为世界上第三个将核动力应用于太空探测国家。","createTime":"1384482280","info1":"","info2":"","info3":"","mlevel":"","musicurl":[],"pic_list":["http:\/\/ww3.sinaimg.cn\/thumbnail\/bfbbe782jw1ealhsvim41j20ca08574w.jpg"],"praiseCount":"0","reportCount":"0","source":"vivo_Xplay","userId":"fed079a4aadf5ccdb6041b69b6669c3c","videourl":[],"weiboId":"12151b090e2f81906cc5b2e04539aa4e","weiboUrl":"2723b4b64e693bb4ed7018d938a19d53"}]
[{"beCommentWeiboId":"d41d8cd98f00b204e9800998ecf8427e","beForwardWeiboId":"d41d8cd98f00b204e9800998ecf8427e","catchTime":"1387807877","commentCount":"0","content":"【嫦娥三号探测器将采用核动力推进技术不逊美国】11月15日，我国嫦娥三号月球探测器发射在即，为能够在月球上过夜；嫦娥三号需要长时间经受严寒带来极大挑战。为了突破这一难关，嫦娥三号，将携带核能电池飞天。如能成功，就将使我国成为继美俄之后，成为世界上第三个将核动力应用于太空探测国家。","createTime":"1384482279","info1":"","info2":"","info3":"","mlevel":"","musicurl":[],"pic_list":["http:\/\/ww1.sinaimg.cn\/thumbnail\/d8ef3a16jw1ealhsvkzojj20ca08574w.jpg"],"praiseCount":"0","reportCount":"0","source":"皮皮时光机","userId":"742be6712c336eb00d8ccb611bd93ae2","videourl":[],"weiboId":"41361bcd22369980daee0efb1075b39e","weiboUrl":"977717340b092b42008e80d4c8f17053"}]
[{"beCommentWeiboId":"d41d8cd98f00b204e9800998ecf8427e","beForwardWeiboId":"d41d8cd98f00b204e9800998ecf8427e","catchTime":"1387807877","commentCount":"0","content":"嫦娥三号探测器将采用核动力推进技术不逊美国分享自@新浪军事http://t.cn/8DF2v8t","createTime":"1384482265","info1":"","info2":"","info3":"","mlevel":"","musicurl":[],"pic_list":["http:\/\/ww3.sinaimg.cn\/thumbnail\/bbf36360jw1ealhsm07mkj20ci08b75a.jpg"],"praiseCount":"0","reportCount":"0","source":"新浪军事","userId":"9769a5cf57e8116c3d8f996b771a68ec","videourl":[],"weiboId":"468de0e092e1cd223ef9c5f49f12c869","weiboUrl":"f6063ebfa4282f2768d28d27f1feec1d"}]
[{"beCommentWeiboId":"d41d8cd98f00b204e9800998ecf8427e","beForwardWeiboId":"d41d8cd98f00b204e9800998ecf8427e","catchTime":"1387807877","commentCount":"0","content":"嫦娥三号月球探测器将于年底择机发射关注概念股股票频道和讯网http://t.cn/8DFAs77","createTime":"1384482245","info1":"","info2":"","info3":"","mlevel":"","musicurl":[],"pic_list":["http:\/\/ww4.sinaimg.cn\/square\/613de4e1jw1ealhs7bsd0j203t032t8o.jpg"],"praiseCount":"0","reportCount":"0","source":"百度分享","userId":"8a74e8f02724fe810e0eb0251695e41b","videourl":[],"weiboId":"29ae251e9060b3120713130e68ccafbf","weiboUrl":"a6badf990cddee50c1c23d5057d126e3"}]
[{"beCommentWeiboId":"d41d8cd98f00b204e9800998ecf8427e","beForwardWeiboId":"d41d8cd98f00b204e9800998ecf8427e","catchTime":"1387807877","commentCount":"0","content":"【嫦娥三号探测器将采用核动力推进技术不逊美国2013111417:38来源：人民网1人参与1条评论字号：小中大这是嫦娥三号月球探测器，包括着陆器和巡视器，是我国研制的首次在外天体实施软着陆的航天器。新华社发资料图片　　我国嫦娥三号月球探测器发射在即，http://t.cn/8DFADr8","createTime":"1384482201","info1":"","info2":"","info3":"","mlevel":"","musicurl":[],"pic_list":["http:\/\/ww4.sinaimg.cn\/thumbnail\/65ac5d30jw1ealhrihaeej20ci08b75a.jpg"],"praiseCount":"0","reportCount":"0","source":"分享按钮","userId":"c1efe85b633351b71e9ede043588aff9","videourl":[],"weiboId":"201f2e86c8c182633714ba719c669b4a","weiboUrl":"3a4f8cdbe8747393b2b334c4f64ae77b"}]
[{"beCommentWeiboId":"d41d8cd98f00b204e9800998ecf8427e","beForwardWeiboId":"d41d8cd98f00b204e9800998ecf8427e","catchTime":"1387807877","commentCount":"0","content":"【嫦娥三号探测器将采用核动力推进技术不逊美国】11月15日，我国嫦娥三号月球探测器发射在即，为能够在月球上过夜；嫦娥三号需要长时间经受严寒带来极大挑战。为了突破这一难关，嫦娥三号，将携带核能电池飞天。如能成功，就将使我国成为继美俄之后，成为世界上第三个将核动力应用于太空探测国家。","createTime":"1384482065","info1":"","info2":"","info3":"","mlevel":"","musicurl":[],"pic_list":["http:\/\/ww4.sinaimg.cn\/thumbnail\/e06b2566jw1ealhp5hm4aj20ca08574w.jpg"],"praiseCount":"0","reportCount":"0","source":"vivo_Xplay","userId":"197f94f5990b00ec7be3671a2b65f470","videourl":[],"weiboId":"6879f58524eea0c96ee786fdacdb2fdd","weiboUrl":"1776524d2e9e5c20dfd69e23af360a8a"}]
[{"beCommentWeiboId":"d41d8cd98f00b204e9800998ecf8427e","beForwardWeiboId":"d41d8cd98f00b204e9800998ecf8427e","catchTime":"1387807877","commentCount":"0","content":"【嫦娥三号探测器将采用核动力推进技术不逊美国】11月15日，我国嫦娥三号月球探测器发射在即，为能够在月球上过夜；嫦娥三号需要长时间经受严寒带来极大挑战。为了突破这一难关，嫦娥三号，将携带核能电池飞天。如能成功，就将使我国成为继美俄之后，成为世界上第三个将核动力应用于太空探测国家。","createTime":"1384481981","info1":"","info2":"","info3":"","mlevel":"","musicurl":[],"pic_list":["http:\/\/ww3.sinaimg.cn\/thumbnail\/e45f0c23jw1ealhnp9g7jj20ca08574w.jpg"],"praiseCount":"0","reportCount":"0","source":"vivo_Xplay","userId":"ca651ac5a90a35dda93c87332a121c5d","videourl":[],"weiboId":"25771a4c466cafcc6ec3937b10d81119","weiboUrl":"17fb75559ea10e689103d1c32db79976"}]
[{"beCommentWeiboId":"d41d8cd98f00b204e9800998ecf8427e","beForwardWeiboId":"d41d8cd98f00b204e9800998ecf8427e","catchTime":"1387807878","commentCount":"0","content":"【嫦娥三号探测器采用核动力推进代表世界最高水平】这是嫦娥三号月球探测器，包括着陆器和巡视器，是我国研制的首次在外天体实施软着陆的航天器。图片来源：新华社)我国嫦娥三号月球探测器发射在即，为了能够在月球上过夜;嫦娥三号需要长时间经分享自@凤凰网http://t.cn/8DFApWB","createTime":"1384481858","info1":"","info2":"","info3":"","mlevel":"","musicurl":[],"pic_list":[],"praiseCount":"0","reportCount":"0","source":"分享按钮","userId":"57d5922584a2cd7fadcb8782ec2b7e2f","videourl":[],"weiboId":"4cb71e996944110103ca3dfee0e33886","weiboUrl":"14595a4f5a388139d653013f2fe67ccb"}]
[{"beCommentWeiboId":"d41d8cd98f00b204e9800998ecf8427e","beForwardWeiboId":"d41d8cd98f00b204e9800998ecf8427e","catchTime":"1387807878","commentCount":"0","content":"【嫦娥三号探测器将采用核动力推进技术不逊美国】11月15日，我国嫦娥三号月球探测器发射在即，为能够在月球上过夜；嫦娥三号需要长时间经受严寒带来极大挑战。为了突破这一难关，嫦娥三号，将携带核能电池飞天。如能成功，就将使我国成为继美俄之后，成为世界上第三个将核动力应用于太空探测国家。","createTime":"1384481814","info1":"","info2":"","info3":"","mlevel":"","musicurl":[],"pic_list":["http:\/\/ww1.sinaimg.cn\/thumbnail\/e4828b4bjw1ealhktho1mj20ca08574w.jpg"],"praiseCount":"0","reportCount":"0","source":"vivo_Xplay","userId":"9026b0a07eca36ff4f2bc4d9f65b4316","videourl":[],"weiboId":"8f5bf598e25575480b06d6854acc965b","weiboUrl":"b069e72640452c732bfe3d5bd02509e4"}]
[{"beCommentWeiboId":"d41d8cd98f00b204e9800998ecf8427e","beForwardWeiboId":"d41d8cd98f00b204e9800998ecf8427e","catchTime":"1387807878","commentCount":"0","content":"昨天跟大盘说嫦娥三号即将升天，有人跟踪航天股吗？","createTime":"1384481757","info1":"","info2":"","info3":"","mlevel":"","musicurl":[],"pic_list":["http:\/\/ww1.sinaimg.cn\/thumbnail\/e6b2245bjw1ealhjtr7z9j208m0643zk.jpg"],"praiseCount":"0","reportCount":"0","source":"FaWave","userId":"332ef059fa17e63ebd7180e3fc83b239","videourl":[],"weiboId":"8ed4b5dd97e034983229603bee6a0d31","weiboUrl":"015686e4b68e52571e67c99ca82ade0d"}]
[{"beCommentWeiboId":"d41d8cd98f00b204e9800998ecf8427e","beForwardWeiboId":"d41d8cd98f00b204e9800998ecf8427e","catchTime":"1387807878","commentCount":"0","content":"昨天跟大盘说嫦娥三号即将升天，有人跟踪航天股吗？","createTime":"1384481756","info1":"","info2":"","info3":"","mlevel":"","musicurl":[],"pic_list":["http:\/\/ww1.sinaimg.cn\/thumbnail\/c516a4e1jw1ealhjt6v7gj208m0643zk.jpg"],"praiseCount":"0","reportCount":"0","source":"FaWave","userId":"27bb274a113192ece4d274c184c8518d","videourl":[],"weiboId":"7ac3c7a0069340be2704cd4b54fb3321","weiboUrl":"b15b3b11c2467e662fa14ec196751a6f"}]
[{"beCommentWeiboId":"d41d8cd98f00b204e9800998ecf8427e","beForwardWeiboId":"d41d8cd98f00b204e9800998ecf8427e","catchTime":"1387807878","commentCount":"0","content":"昨天跟大盘说嫦娥三号即将升天，有人跟踪航天股吗？","createTime":"1384481756","info1":"","info2":"","info3":"","mlevel":"","musicurl":[],"pic_list":["http:\/\/ww1.sinaimg.cn\/thumbnail\/e55d652bjw1ealhjsz5n8j208m0643zk.jpg"],"praiseCount":"0","reportCount":"0","source":"FaWave","userId":"c33c04d435254754ed998e0f5556d562","videourl":[],"weiboId":"cbf6e6949180bbda56513eac6f654b9e","weiboUrl":"496727169f79fefc1c2c15d7fb1c2cc1"}]
[{"beCommentWeiboId":"d41d8cd98f00b204e9800998ecf8427e","beForwardWeiboId":"d41d8cd98f00b204e9800998ecf8427e","catchTime":"1387807878","commentCount":"0","content":"昨天跟大盘说嫦娥三号即将升天，有人跟踪航天股吗？","createTime":"1384481756","info1":"","info2":"","info3":"","mlevel":"","musicurl":[],"pic_list":["http:\/\/ww2.sinaimg.cn\/thumbnail\/e4eef588jw1ealhjsymrpj208m0643zk.jpg"],"praiseCount":"0","reportCount":"0","source":"FaWave","userId":"ec6aa5cdb02d626f9fc9194b50c196ee","videourl":[],"weiboId":"20d036f7dea3aa6493c66dc0430e4ddb","weiboUrl":"29309c6ab9da3b87318e696fa44bc753"}]
[{"beCommentWeiboId":"d41d8cd98f00b204e9800998ecf8427e","beForwardWeiboId":"d41d8cd98f00b204e9800998ecf8427e","catchTime":"1387807878","commentCount":"0","content":"昨天跟大盘说嫦娥三号即将升天，有人跟踪航天股吗？","createTime":"1384481756","info1":"","info2":"","info3":"","mlevel":"","musicurl":[],"pic_list":["http:\/\/ww3.sinaimg.cn\/thumbnail\/e547ba1djw1ealhjsz3pjj208m0643zk.jpg"],"praiseCount":"0","reportCount":"0","source":"FaWave","userId":"95c7f0a979c02b8d9b14459e013dcfe6","videourl":[],"weiboId":"4c9d5fa78e89bae24bbbde8e587f21b9","weiboUrl":"2dc15b205579321b365e5740e457bc5c"}]
[{"beCommentWeiboId":"d41d8cd98f00b204e9800998ecf8427e","beForwardWeiboId":"d41d8cd98f00b204e9800998ecf8427e","catchTime":"1387807878","commentCount":"0","content":"昨天跟大盘说嫦娥三号即将升天，有人跟踪航天股吗？","createTime":"1384481756","info1":"","info2":"","info3":"","mlevel":"","musicurl":[],"pic_list":["http:\/\/ww1.sinaimg.cn\/thumbnail\/e7f7be06jw1ealhjsy1nuj208m0643zk.jpg"],"praiseCount":"0","reportCount":"0","source":"FaWave","userId":"795f611d9041acc3d0e65faa1f0e90c1","videourl":[],"weiboId":"a6990b3b8bfa0c084a2f581432299673","weiboUrl":"7e9f1c38dfca69224bb52a3753775731"}]
[{"beCommentWeiboId":"d41d8cd98f00b204e9800998ecf8427e","beForwardWeiboId":"d41d8cd98f00b204e9800998ecf8427e","catchTime":"1387807878","commentCount":"0","content":"昨天跟大盘说嫦娥三号即将升天，有人跟踪航天股吗？","createTime":"1384481756","info1":"","info2":"","info3":"","mlevel":"","musicurl":[],"pic_list":["http:\/\/ww2.sinaimg.cn\/thumbnail\/e52c7aadjw1ealhjsxjx8j208m0643zk.jpg"],"praiseCount":"0","reportCount":"0","source":"FaWave","userId":"03627f6efb82cd9274dade77e7dbcc2b","videourl":[],"weiboId":"6fa86fd197464754afe6ff2c306d211b","weiboUrl":"388dd9db377c77a662f5cd7447156a7a"}]
[{"beCommentWeiboId":"d41d8cd98f00b204e9800998ecf8427e","beForwardWeiboId":"d41d8cd98f00b204e9800998ecf8427e","catchTime":"1387807878","commentCount":"0","content":"昨天跟大盘说嫦娥三号即将升天，有人跟踪航天股吗？","createTime":"1384481756","info1":"","info2":"","info3":"","mlevel":"","musicurl":[],"pic_list":["http:\/\/ww2.sinaimg.cn\/thumbnail\/e529c712jw1ealhjsz5m5j208m0643zk.jpg"],"praiseCount":"0","reportCount":"0","source":"FaWave","userId":"902c6f71cb9aaf35a9c84491ab5460bb","videourl":[],"weiboId":"49d1394ac2f6ca746ac26f6cc472f945","weiboUrl":"745266ae7fa32452523c8ef028770b35"}]
[{"beCommentWeiboId":"d41d8cd98f00b204e9800998ecf8427e","beForwardWeiboId":"d41d8cd98f00b204e9800998ecf8427e","catchTime":"1387807878","commentCount":"0","content":"昨天跟大伙说嫦娥三号即将升天，有人跟踪航天股吗？","createTime":"1384481661","info1":"","info2":"","info3":"","mlevel":"","musicurl":[],"pic_list":["http:\/\/ww2.sinaimg.cn\/thumbnail\/aaa612c4jw1ealhi5zvmij208d07k0tt.jpg"],"praiseCount":"0","reportCount":"0","source":"FaWave","userId":"c1b562ef8c592137f402b77ce0db92c9","videourl":[],"weiboId":"e80861198b1a844a8b194023333946e1","weiboUrl":"bbc9138849649b7c5c893293e40a0dc7"}]
[{"beCommentWeiboId":"d41d8cd98f00b204e9800998ecf8427e","beForwardWeiboId":"d41d8cd98f00b204e9800998ecf8427e","catchTime":"1387807878","commentCount":"0","content":"昨天跟大伙说嫦娥三号即将升天，有人跟踪航天股吗？","createTime":"1384481648","info1":"","info2":"","info3":"","mlevel":"","musicurl":[],"pic_list":["http:\/\/ww3.sinaimg.cn\/thumbnail\/a9555b78jw1ealhhxgb9oj208d07k0tt.jpg"],"praiseCount":"0","reportCount":"0","source":"FaWave","userId":"61a31af7a844bc71be52a4b8fdfaf4f6","videourl":[],"weiboId":"dde98ead9af410c24aec636863f6470b","weiboUrl":"c7ba05637ab606a0dae94a0975c589a9"}]
[{"beCommentWeiboId":"d41d8cd98f00b204e9800998ecf8427e","beForwardWeiboId":"d41d8cd98f00b204e9800998ecf8427e","catchTime":"1387807878","commentCount":"0","content":"昨天跟大伙说嫦娥三号即将升天，有人跟踪航天股吗？","createTime":"1384481645","info1":"","info2":"","info3":"","mlevel":"","musicurl":[],"pic_list":["http:\/\/ww2.sinaimg.cn\/thumbnail\/63578410jw1ealhhvp1zzj208d07k0tt.jpg"],"praiseCount":"0","reportCount":"0","source":"FaWave","userId":"53dc8645dd176229569dc7056935a1aa","videourl":[],"weiboId":"d84a1b588b23faa9aa51177860279913","weiboUrl":"6a287a2afed6b8043eeb77db1430fcb3"}]
[{"beCommentWeiboId":"d41d8cd98f00b204e9800998ecf8427e","beForwardWeiboId":"d41d8cd98f00b204e9800998ecf8427e","catchTime":"1387807878","commentCount":"0","content":"昨天跟大伙说嫦娥三号即将升天，有人跟踪航天股吗？","createTime":"1384481643","info1":"","info2":"","info3":"","mlevel":"","musicurl":[],"pic_list":["http:\/\/ww1.sinaimg.cn\/thumbnail\/ab3d87d2jw1ealhhuwma5j208d07k0tt.jpg"],"praiseCount":"1","reportCount":"0","source":"FaWave","userId":"df7c59cc18c9373d291dc42883c2a6ee","videourl":[],"weiboId":"d206af3d367d7e8a4e847c4fb055fe71","weiboUrl":"b760bb4be1b52937327e16e2221928ae"}]
[{"beCommentWeiboId":"d41d8cd98f00b204e9800998ecf8427e","beForwardWeiboId":"d41d8cd98f00b204e9800998ecf8427e","catchTime":"1387807878","commentCount":"0","content":"昨天跟大伙说嫦娥三号即将升天，有人跟踪航天股吗？","createTime":"1384481640","info1":"","info2":"","info3":"","mlevel":"","musicurl":[],"pic_list":["http:\/\/ww1.sinaimg.cn\/thumbnail\/a865263ejw1ealhhsgcr5j208d07k0tt.jpg"],"praiseCount":"0","reportCount":"0","source":"FaWave","userId":"8d4e443aee8b571c69802fe817b2dd13","videourl":[],"weiboId":"cc020b2e81372a70735f1d94bb11c9d5","weiboUrl":"d575e8d6bda655fbc796cb903f4b84f4"}]
[{"beCommentWeiboId":"d41d8cd98f00b204e9800998ecf8427e","beForwardWeiboId":"d41d8cd98f00b204e9800998ecf8427e","catchTime":"1387807878","commentCount":"0","content":"昨天跟大伙说嫦娥三号即将升天，有人跟踪航天股吗？","createTime":"1384481617","info1":"","info2":"","info3":"","mlevel":"","musicurl":[],"pic_list":["http:\/\/ww2.sinaimg.cn\/thumbnail\/ab317780jw1ealhhefb9kj208d07k0tt.jpg"],"praiseCount":"0","reportCount":"0","source":"FaWave","userId":"0f56b795d62c680e64ecaa721e51cd70","videourl":[],"weiboId":"56916d818cd37ef2c23c4a37481b5223","weiboUrl":"e06ef8698ef478af8a533a8e1dde068d"}]
[{"beCommentWeiboId":"d41d8cd98f00b204e9800998ecf8427e","beForwardWeiboId":"d41d8cd98f00b204e9800998ecf8427e","catchTime":"1387807878","commentCount":"0","content":"昨天跟大伙说嫦娥三号即将升天，有人跟踪航天股吗？","createTime":"1384481607","info1":"","info2":"","info3":"","mlevel":"","musicurl":[],"pic_list":["http:\/\/ww2.sinaimg.cn\/thumbnail\/86dd0c66jw1ealhh7vo4qj208d07k0tt.jpg"],"praiseCount":"0","reportCount":"0","source":"FaWave","userId":"1903c83dbebda236ca673e45b25e162a","videourl":[],"weiboId":"4373cba4f74bb79def13153f7fba5022","weiboUrl":"ab49e2619ce025e80a40a40a45505f66"}]
[{"beCommentWeiboId":"d41d8cd98f00b204e9800998ecf8427e","beForwardWeiboId":"d41d8cd98f00b204e9800998ecf8427e","catchTime":"1387807878","commentCount":"0","content":"昨天跟大伙说嫦娥三号即将升天，有人跟踪航天股吗？","createTime":"1384481602","info1":"","info2":"","info3":"","mlevel":"","musicurl":[],"pic_list":["http:\/\/ww4.sinaimg.cn\/thumbnail\/a805d770jw1ealhh4mu8kj208d07k0tt.jpg"],"praiseCount":"0","reportCount":"0","source":"FaWave","userId":"17e46d1783c01a6efb1f3a9b99526db9","videourl":[],"weiboId":"e39dbc228a98c0c777ae72572c240d27","weiboUrl":"92afd3677eab1f0d4709b2d41f4836c2"}]
[{"beCommentWeiboId":"d41d8cd98f00b204e9800998ecf8427e","beForwardWeiboId":"d41d8cd98f00b204e9800998ecf8427e","catchTime":"1387807878","commentCount":"0","content":"昨天跟大伙说嫦娥三号即将升天，有人跟踪航天股吗？","createTime":"1384481602","info1":"","info2":"","info3":"","mlevel":"","musicurl":[],"pic_list":["http:\/\/ww3.sinaimg.cn\/thumbnail\/a685a637jw1ealhh56b8rj208d07k0tt.jpg"],"praiseCount":"0","reportCount":"0","source":"FaWave","userId":"dd55f8274304e96ed0bc2abf1354ea79","videourl":[],"weiboId":"f9fe8e6619e9326e9eefc568c2e41884","weiboUrl":"29c40b4cdb39ddbfe8f3907163ff0231"}]
[{"beCommentWeiboId":"d41d8cd98f00b204e9800998ecf8427e","beForwardWeiboId":"d41d8cd98f00b204e9800998ecf8427e","catchTime":"1387807878","commentCount":"0","content":"昨天跟大伙说嫦娥三号即将升天，有人跟踪航天股吗？","createTime":"1384481597","info1":"","info2":"","info3":"","mlevel":"","musicurl":[],"pic_list":["http:\/\/ww1.sinaimg.cn\/thumbnail\/a8512ee0jw1ealhh1ydb2j208d07k0tt.jpg"],"praiseCount":"0","reportCount":"0","source":"FaWave","userId":"f520ff4e5aae80aafc1b9b4fd1cdeeff","videourl":[],"weiboId":"8d8fd31ffc4fd6dc4f0bd41071a3b486","weiboUrl":"a323ee56acc11ac921b08180351bfa1a"}]
[{"beCommentWeiboId":"d41d8cd98f00b204e9800998ecf8427e","beForwardWeiboId":"d41d8cd98f00b204e9800998ecf8427e","catchTime":"1387807879","commentCount":"0","content":"昨天跟大伙说嫦娥三号即将升天，有人跟踪航天股吗？","createTime":"1384481591","info1":"","info2":"","info3":"","mlevel":"","musicurl":[],"pic_list":["http:\/\/ww3.sinaimg.cn\/thumbnail\/ab216f1ejw1ealhgxzyauj208d07k0tt.jpg"],"praiseCount":"0","reportCount":"0","source":"FaWave","userId":"f5e5b0420d8a635a5da82f259098b601","videourl":[],"weiboId":"25ce4e96a9d6a52aaef31d85697c3233","weiboUrl":"ec05ff588ab5d84db7f50acfcfde51a4"}]
[{"beCommentWeiboId":"d41d8cd98f00b204e9800998ecf8427e","beForwardWeiboId":"d41d8cd98f00b204e9800998ecf8427e","catchTime":"1387807879","commentCount":"0","content":"昨天跟大伙说嫦娥三号即将升天，有人跟踪航天股吗？","createTime":"1384481588","info1":"","info2":"","info3":"","mlevel":"","musicurl":[],"pic_list":["http:\/\/ww3.sinaimg.cn\/thumbnail\/a686635bjw1ealhgvyfp1j208d07k0tt.jpg"],"praiseCount":"0","reportCount":"0","source":"FaWave","userId":"d9a23dfd0a2472b5f957e0691a8c561b","videourl":[],"weiboId":"3df480556f94833ab168f9785eb11bce","weiboUrl":"7e48a8a61d6834cb49b2f2c2387514f6"}]
[{"beCommentWeiboId":"d41d8cd98f00b204e9800998ecf8427e","beForwardWeiboId":"d41d8cd98f00b204e9800998ecf8427e","catchTime":"1387807879","commentCount":"0","content":"昨天跟大伙说嫦娥三号即将升天，有人跟踪航天股吗？","createTime":"1384481577","info1":"","info2":"","info3":"","mlevel":"","musicurl":[],"pic_list":["http:\/\/ww1.sinaimg.cn\/thumbnail\/a85407aajw1ealhgp8opkj208d07k0tt.jpg"],"praiseCount":"0","reportCount":"0","source":"FaWave","userId":"47b48be9dc850023a754019bd83f4887","videourl":[],"weiboId":"8ae2bb6a28f31d8b8fcbfefda9612679","weiboUrl":"4af315da59d9d74188213868742c46ef"}]
[{"beCommentWeiboId":"d41d8cd98f00b204e9800998ecf8427e","beForwardWeiboId":"d41d8cd98f00b204e9800998ecf8427e","catchTime":"1387807879","commentCount":"0","content":"昨天跟大伙说嫦娥三号即将升天，有人跟踪航天股吗？","createTime":"1384481577","info1":"","info2":"","info3":"","mlevel":"","musicurl":[],"pic_list":["http:\/\/ww1.sinaimg.cn\/thumbnail\/a83bbc8ejw1ealhgp4y22j208d07k0tt.jpg"],"praiseCount":"0","reportCount":"0","source":"FaWave","userId":"a733a61aa133b0556c45bb50aecfa908","videourl":[],"weiboId":"99794053bc9f2ba84784ac2ca514b987","weiboUrl":"3ee6112c4682f01969743e570d390efe"}]
[{"beCommentWeiboId":"d41d8cd98f00b204e9800998ecf8427e","beForwardWeiboId":"d41d8cd98f00b204e9800998ecf8427e","catchTime":"1387807879","commentCount":"0","content":"昨天跟大伙说嫦娥三号即将升天，有人跟踪航天股吗？","createTime":"1384481572","info1":"","info2":"","info3":"","mlevel":"","musicurl":[],"pic_list":["http:\/\/ww2.sinaimg.cn\/thumbnail\/a8641a9ejw1ealhgm49wzj208d07k0tt.jpg"],"praiseCount":"0","reportCount":"0","source":"FaWave","userId":"6e917d79a2ad3445d364d4b3c7a73c35","videourl":[],"weiboId":"8521b8cb01326ba348944db0b8bbf379","weiboUrl":"4b808d281abb78a8ef2181b46b34a4c9"}]
[{"beCommentWeiboId":"d41d8cd98f00b204e9800998ecf8427e","beForwardWeiboId":"d41d8cd98f00b204e9800998ecf8427e","catchTime":"1387807879","commentCount":"0","content":"昨天跟大伙说嫦娥三号即将升天，有人跟踪航天股吗？","createTime":"1384481569","info1":"","info2":"","info3":"","mlevel":"","musicurl":[],"pic_list":["http:\/\/ww4.sinaimg.cn\/thumbnail\/79b1679fjw1ealhgkhlc2j208d07k0tt.jpg"],"praiseCount":"0","reportCount":"0","source":"FaWave","userId":"1550f0cae739ab61f10e52393dda6654","videourl":[],"weiboId":"99f26bc2a947b384423dfa6f768bbac6","weiboUrl":"d0e7d01089cd7c77e8f36ca91c913eef"}]
[{"beCommentWeiboId":"d41d8cd98f00b204e9800998ecf8427e","beForwardWeiboId":"d41d8cd98f00b204e9800998ecf8427e","catchTime":"1387807879","commentCount":"0","content":"昨天跟大伙说嫦娥三号即将升天，有人跟踪航天股吗？","createTime":"1384481564","info1":"","info2":"","info3":"","mlevel":"","musicurl":[],"pic_list":["http:\/\/ww4.sinaimg.cn\/thumbnail\/a868bfe0jw1ealhgh05e2j208d07k0tt.jpg"],"praiseCount":"0","reportCount":"0","source":"FaWave","userId":"309d9e4cbd233215de9d2c75412147a4","videourl":[],"weiboId":"0b549f8bea4004ca676b803e42bee630","weiboUrl":"701b340cc62fd14aeb8428ad06dd3324"}]
[{"beCommentWeiboId":"d41d8cd98f00b204e9800998ecf8427e","beForwardWeiboId":"d41d8cd98f00b204e9800998ecf8427e","catchTime":"1387807879","commentCount":"0","content":"昨天跟大伙说嫦娥三号即将升天，有人跟踪航天股吗？","createTime":"1384481556","info1":"","info2":"","info3":"","mlevel":"","musicurl":[],"pic_list":["http:\/\/ww3.sinaimg.cn\/thumbnail\/5e94689djw1ealhgc557ej208d07k0tt.jpg"],"praiseCount":"0","reportCount":"0","source":"FaWave","userId":"943f3bf49e16fddfb63a9c6cf0bdea30","videourl":[],"weiboId":"43f4f8f662a59d09ed0262aa289250ae","weiboUrl":"cabdce097f842f998986e7d23debe3f1"}]
[{"beCommentWeiboId":"d41d8cd98f00b204e9800998ecf8427e","beForwardWeiboId":"d41d8cd98f00b204e9800998ecf8427e","catchTime":"1387807879","commentCount":"0","content":"嫦娥三号探测器将采用核动力推进技术不逊美国","createTime":"1384481537","info1":"","info2":"","info3":"","mlevel":"","musicurl":[],"pic_list":["http:\/\/ww2.sinaimg.cn\/thumbnail\/63b43d98jw1ealhfy3mttj20ci08b75a.jpg"],"praiseCount":"0","reportCount":"0","source":"360浏览器超速版","userId":"48d4fe1f1a306e72dea000c5cc73c673","videourl":[],"weiboId":"33023142634c4a1690b08cdc1e0fcefe","weiboUrl":"ac725bb941f5fa36c335152602ffefb1"}]
[{"beCommentWeiboId":"d41d8cd98f00b204e9800998ecf8427e","beForwardWeiboId":"d41d8cd98f00b204e9800998ecf8427e","catchTime":"1387807879","commentCount":"0","content":"不错。嫦娥三号探测器采用核动力推进技术不逊于美国爱问http://t.cn/8DFAhxv","createTime":"1384481347","info1":"","info2":"","info3":"","mlevel":"","musicurl":[],"pic_list":[],"praiseCount":"0","reportCount":"0","source":"MEIZU MX3","userId":"3f8bda161e21d063c77dd4e515569d4d","videourl":[],"weiboId":"fead07838b52232419dc0807c7da3a08","weiboUrl":"31fd3d1f23889ccb0109034cb148df0c"}]
[{"beCommentWeiboId":"d41d8cd98f00b204e9800998ecf8427e","beForwardWeiboId":"d41d8cd98f00b204e9800998ecf8427e","catchTime":"1387807879","commentCount":"0","content":"真的吗？——看到人民匹夫的博文《[转载]嫦娥三号探测器将采用核动力推进技术不逊美国》有感而发的评论。http://t.cn/8DFwm8g","createTime":"1384481116","info1":"","info2":"","info3":"","mlevel":"","musicurl":[],"pic_list":[],"praiseCount":"0","reportCount":"0","source":"新浪博客","userId":"f7ae978629ab0e25ca56156d22a1ab55","videourl":[],"weiboId":"b22bd781bc3fc501bd6f266abef0b06c","weiboUrl":"e710748669cd276293620a2713981fe6"}]
[{"beCommentWeiboId":"d41d8cd98f00b204e9800998ecf8427e","beForwardWeiboId":"d41d8cd98f00b204e9800998ecf8427e","catchTime":"1387807879","commentCount":"0","content":"今年年底，令人瞩目的嫦娥三号月球探测器即将发射升空，从而实现我国探月工程二期重要的软着陆任务。而就在近期举办的2013年中国国际工业博览会上，国产月球车的模型已经提前与公众...http://t.cn/8DFwCtY#立方网#","createTime":"1384480861","info1":"","info2":"","info3":"","mlevel":"","musicurl":[],"pic_list":[],"praiseCount":"0","reportCount":"0","source":"立方网","userId":"67025cda6fe2fd3abce13275eae7037a","videourl":[],"weiboId":"5a53b9364eb17ae015a112aefabacd13","weiboUrl":"0d5eef480363b829e3b17b6bb186694e"}]
[{"beCommentWeiboId":"d41d8cd98f00b204e9800998ecf8427e","beForwardWeiboId":"d41d8cd98f00b204e9800998ecf8427e","catchTime":"1387807879","commentCount":"0","content":"【嫦娥三号探测器采用核动力推进代表世界最高水平】这是嫦娥三号月球探测器，包括着陆器和巡视器，是我国研制的首次在外天体实施软着陆的航天器。图片来源：新华社)我国嫦娥三号月球探测器发射在即，为了能够在月球上过夜;嫦娥三号需要长时间经分享自@凤凰网http://t.cn/8DFwKGe","createTime":"1384480833","info1":"","info2":"","info3":"","mlevel":"","musicurl":[],"pic_list":["http:\/\/ww1.sinaimg.cn\/thumbnail\/e4b45abfjw1ealh3szvowj20ci08b75a.jpg"],"praiseCount":"0","reportCount":"0","source":"分享按钮","userId":"9e8f1a485e723d22111613f561ce35e6","videourl":[],"weiboId":"4e9f4fd7f59e1a37242e46012ad26060","weiboUrl":"83fda99541cbfdf05cb7f6309f43cdeb"}]
