<?xml version="1.0" encoding="UTF-8"?><extraction><clueid>77611668</clueid><fullpath><![CDATA[http://s.weibo.com/weibo/%25E7%2590%2586%25E5%258E%25BF%2520%25E5%259C%25B0%25E9%259C%2587&nodup=1&page=6]]></fullpath><realpath><![CDATA[http://s.weibo.com/weibo/%25E7%2590%2586%25E5%258E%25BF%2520%25E5%259C%25B0%25E9%259C%2587&nodup=1&page=6]]></realpath><theme>理县-地震</theme><middle>default</middle><createdate>2014-6-9 11:26:38</createdate><baseURI><bucketBaseURI><bucketName>lixian</bucketName><uri><![CDATA[http://s.weibo.com/weibo/%25E7%2590%2586%25E5%258E%25BF%2520%25E5%259C%25B0%25E9%259C%2587&nodup=1&page=6]]></uri></bucketBaseURI></baseURI>
<lixian><item><mid>3701707299067851</mid></item><item><mid>3701657668098755</mid></item><item><mid>3701593697273268</mid></item><item><mid>3701469133507920</mid></item><item><mid>3701141521025224</mid></item><item><mid>3701080325679902</mid></item><item><mid>3701035477158953</mid></item><item><mid>3700848411155702</mid></item><item><mid>3700748451590065</mid></item><item><mid>3700397745268105</mid></item><item><mid>3700278580287934</mid></item><item><mid>3700276084827164</mid></item><item><mid>3700274839394247</mid></item><item><mid>3700273584925632</mid></item><item><mid>3700272473726452</mid></item><item><mid>3700267746991390</mid></item></lixian></extraction>